gadm/__init__.py
gadm/custom_types.py
gadm/gadm_downloader.py
gadm/utils.py
gadm/version.py
gadm-0.0.5.dist-info/LICENSE
gadm-0.0.5.dist-info/METADATA
gadm-0.0.5.dist-info/WHEEL
gadm-0.0.5.dist-info/top_level.txt
gadm-0.0.5.dist-info/RECORD
