Metadata-Version: 2.1
Name: gadm
Version: 0.0.5
Summary: package to get boundaries data from GADM,  the database of global Administrative Areas.
Home-page: https://github.com/xmba15/gadm
Author: Ba Tran
Classifier: Development Status :: 3 - Alpha
Classifier: Intended Audience :: Developers
Classifier: Programming Language :: Python :: 3
Classifier: Programming Language :: Python :: 3.6
Classifier: Programming Language :: Python :: 3.7
Classifier: Programming Language :: Python :: 3.8
Classifier: Programming Language :: Python :: 3.9
License-File: LICENSE
Requires-Dist: typing-extensions
Requires-Dist: types-requests
Requires-Dist: types-setuptools
Requires-Dist: pycountry ==22.3.5
Requires-Dist: geopandas ==0.9.0
Requires-Dist: fake-useragent ==1.3.0
Requires-Dist: requests
Requires-Dist: tqdm ==4.64.1
